{
  "name": "TriTone DeepSea",
  "type": "dark",
  "colors": {
    "tab.activeForeground": "#fcfcfd",
    "foreground": "#dae0e7",
    "titleBar.activeForeground": "#dae0e7",
    "activityBar.foreground": "#dae0e7",
    "input.foreground": "#dae0e7",
    "dropdown.foreground": "#dae0e7",
    "sideBarSectionHeader.foreground": "#bac5d2",
    "statusBar.foreground": "#bac5d2",
    "descriptionForeground": "#bac5d2",
    "sideBar.foreground": "#8b98a6",
    "input.placeholderForeground": "#8b98a6",
    "activityBar.inactiveForeground": "#8b98a6",
    "tab.inactiveForeground": "#8b98a6",
    "editorIndentGuide.activeBackground": "#2a333c",
    "dropdown.border": "#2a333c",
    "list.activeSelectionBackground": "#232c36",
    "editorIndentGuide.background": "#232c36",
    "input.border": "#232c36",
    "dropdown.background": "#232c36",
    "titleBar.activeBackground": "#1d262f",
    "titleBar.inactiveBackground": "#1d262f",
    "activityBar.background": "#1d262f",
    "tab.activeBackground": "#1d262f",
    "tree.indentGuidesStroke": "#1d262f",
    "list.inactiveSelectionBackground": "#1d262f",
    "list.hoverBackground": "#1d262f",
    "statusBar.background": "#1d262f",
    "editor.background": "#1d262f",
    "input.background": "#172029",
    "dropdown.listBackground": "#172029",
    "tab.inactiveBackground": "#111a22",
    "panel.background": "#111a22",
    "editorGroupHeader.tabsBackground": "#111a22",
    "sideBar.background": "#111a22",
    "sideBarSectionHeader.background": "#111a22",
    "titleBar.border": "#09141c",
    "activityBar.border": "#09141c",
    "tab.border": "#09141c",
    "panel.border": "#09141c",
    "statusBar.border": "#09141c",
    "sideBarSectionHeader.border": "#09141c",
    "sideBar.border": "#09141c",
    "activityBar.activeBorder": "#5dfec6",
    "tab.activeBorderTop": "#5dfec6",
    "textLink.foreground": "#6fdff6",
    "editor.foreground": "#fcfcfd",
    "editorLineNumber.activeForeground": "#c1d8f2",
    "editorLineNumber.foreground": "#526c85"
  },
  "semanticHighlighting": true,
  "tokenColors": [
    {
      "scope": "variable",
      "settings": {
        "foreground": "#5dfec6"
      }
    },
    {
      "scope": "string",
      "settings": {
        "foreground": "#6fdff6"
      }
    },
    {
      "scope": "keyword",
      "settings": {
        "foreground": "#88b4e0"
      }
    },
    {
      "scope": "comment",
      "settings": {
        "foreground": "#526c85"
      }
    }
  ]
}